{
    "display": {
        "title": {
            "text": "Silver Guantlets",
            "color": "green",
            "bold": false,
            "italic": true
        },
        "description": {
            "text": ""
        },
        "icon": {
            "item": "minecraft:shears",
            "nbt": "{Unbreakable:1b,Damage:38,HideFlags:63}"
        },
        "frame": "task",
        "show_toast": false,
        "announce_to_chat": false,
        "hidden": true
    },
    "criteria": {
        "Impossible": {
            "trigger": "minecraft:impossible"
        }
    },
    "parent": "minecraft:_gear/goron_bracelet"
}